[
  {
    "age": 41,
    "id": 3,
    "name": "小兰",
    "sub": [
      {
        "sub_age": "cccc",
        "sub_name": "小兰sub-1"
      }
    ]
  },
  {
    "age": 23,
    "id": 2,
    "name": "小黄",
    "sub": [
      {
        "sub_age": "bbbb",
        "sub_name": "小黄sub-1"
      }
    ]
  },
  {
    "age": 12,
    "id": 1,
    "name": "小米",
    "sub": [
      {
        "sub_age": "aaaa",
        "sub_name": "小米sub-2"
      },
      {
        "sub_age": "aaaa",
        "sub_name": "小米sub-1"
      },
      {
        "sub_age": "aaaa",
        "sub_name": "小米sub-3"
      }
    ]
  }
]